thotpy/__init__.py
thotpy/call.py
thotpy/castep.py
thotpy/core.py
thotpy/extract.py
thotpy/file.py
thotpy/find.py
thotpy/phonopy.py
thotpy/qe.py
thotpy/text.py
thotpy-5.5.1.dist-info/LICENSE
thotpy-5.5.1.dist-info/METADATA
thotpy-5.5.1.dist-info/WHEEL
thotpy-5.5.1.dist-info/top_level.txt
thotpy-5.5.1.dist-info/RECORD
