Metadata-Version: 2.1
Name: thotpy
Version: 5.5.1
Summary: The Text enHancement & Optimization for scienTific research with Python, or just ThothPy, allows you to create, modify and analyze all kinds of text files, with a special focus on (but not limited to) ab-initio calculations.
Author: Pablo Gila-Herranz
Author-email: pgila001@ikasle.ehu.eus
License: AGPL-3.0
Keywords: python,thot,thotpy,thoth,thothpy,text,inputmaker,DFT,Density Functional Theory,MD,Molecular Dynamics,ab-initio,Quantum ESPRESSO,Phonopy
Classifier: Development Status :: 5 - Production/Stable
Classifier: Natural Language :: English
Classifier: Intended Audience :: Science/Research
Classifier: Programming Language :: Python :: 3
Classifier: Operating System :: POSIX :: Linux
Classifier: Operating System :: Microsoft :: Windows
Classifier: Operating System :: Other OS
Requires-Python: >=3
License-File: LICENSE
Requires-Dist: pandas>=2.2
Requires-Dist: maatpy>=3.1.0
